keops/__init__.py
keops/debug.py
keops/erase.py
keops/info.py
keops/main.py
keops/shrink.py
keops/size.py
keops/src/__init__.py
keops/src/mvt_debugger.py
keops/src/mvt_eraser.py
keops/src/mvt_printer.py
keops/src/mvt_reader.py
keops/src/utils.py
keops_vt-1.0.0.dist-info/LICENSE.md
keops_vt-1.0.0.dist-info/METADATA
keops_vt-1.0.0.dist-info/WHEEL
keops_vt-1.0.0.dist-info/entry_points.txt
keops_vt-1.0.0.dist-info/top_level.txt
keops_vt-1.0.0.dist-info/RECORD
