Metadata-Version: 2.1
Name: keops-vt
Version: 1.0.0
Summary: CLI tool for custom edition and management of Mapbox Vector Tiles in MBTiles format
Author-email: Fran Martín <fmartinrivas2@gmail.com>
License: MIT
Project-URL: Homepage, https://github.com/fmariv/keops-vt
Project-URL: Bug Tracker, https://github.com/fmariv/keops-vt/issues
Keywords: mbtiles,python,vector-tiles
Classifier: Programming Language :: Python :: 3
Classifier: License :: OSI Approved :: MIT License
Classifier: Operating System :: OS Independent
Requires-Python: >=3.7
License-File: LICENSE.md
Requires-Dist: mapbox-vector-tile (~=1.2.1)
Requires-Dist: protobuf (~=3.19.4)
Requires-Dist: geopandas (~=0.12.1)
Requires-Dist: click (~=8.1.3)
Requires-Dist: geojson (~=2.5.0)
Requires-Dist: setuptools (~=58.1.0)
Requires-Dist: docker (~=6.0.1)
Requires-Dist: mkdocs (~=1.4.1)
Requires-Dist: mkdocs-material (~=9.1.0)
Requires-Dist: prettytable (~=3.6.0)
Requires-Dist: halo (~=0.0.31)
